jaegertrace/__init__.py
jaegertrace/conf.py
jaegertrace/exceptions.py
jaegertrace/httpclient.py
jaegertrace/initial_tracer.py
jaegertrace/middleware.py
jaegertrace/request_context.py
jaegertrace/patches/__init__.py
django_jaeger_middleware_plus-0.0.2.dist-info/LICENSE
django_jaeger_middleware_plus-0.0.2.dist-info/METADATA
django_jaeger_middleware_plus-0.0.2.dist-info/WHEEL
django_jaeger_middleware_plus-0.0.2.dist-info/top_level.txt
django_jaeger_middleware_plus-0.0.2.dist-info/RECORD
